PFAS_SAT_InputData/ADInput.py
PFAS_SAT_InputData/AdvWWTInput.py
PFAS_SAT_InputData/CommonData.py
PFAS_SAT_InputData/CompInput.py
PFAS_SAT_InputData/DeepWellInjectionInput.py
PFAS_SAT_InputData/IncomFlowInput.py
PFAS_SAT_InputData/InputData.py
PFAS_SAT_InputData/LandAppInput.py
PFAS_SAT_InputData/LandfillInput.py
PFAS_SAT_InputData/MC.py
PFAS_SAT_InputData/SCWOInput.py
PFAS_SAT_InputData/StabInput.py
PFAS_SAT_InputData/SurfaceWaterReleaseInput.py
PFAS_SAT_InputData/ThermalReactivationInput.py
PFAS_SAT_InputData/ThermalTreatmentInput.py
PFAS_SAT_InputData/WWTInput.py
PFAS_SAT_InputData/__init__.py
PFAS_SAT_InputData/Data/ADInput.csv
PFAS_SAT_InputData/Data/AdvWWTInput.csv
PFAS_SAT_InputData/Data/CommonData.csv
PFAS_SAT_InputData/Data/CompInput.csv
PFAS_SAT_InputData/Data/DeepWellInjectionInput.csv
PFAS_SAT_InputData/Data/IncomFlowInput.csv
PFAS_SAT_InputData/Data/LandAppInput.csv
PFAS_SAT_InputData/Data/LandfillInput.csv
PFAS_SAT_InputData/Data/References.csv
PFAS_SAT_InputData/Data/SCWOInput.csv
PFAS_SAT_InputData/Data/StabInput.csv
PFAS_SAT_InputData/Data/SurfaceWaterReleaseInput.csv
PFAS_SAT_InputData/Data/ThermalReactivationInput - HT.csv
PFAS_SAT_InputData/Data/ThermalReactivationInput.csv
PFAS_SAT_InputData/Data/ThermalTreatmentInput - HT.csv
PFAS_SAT_InputData/Data/ThermalTreatmentInput.csv
PFAS_SAT_InputData/Data/WWTInput.csv
PFAS_SAT_InputData/Data/__init__.py
PFAS_SAT_InputData-0.0.4.dist-info/AUTHORS.rst
PFAS_SAT_InputData-0.0.4.dist-info/LICENSE.md
PFAS_SAT_InputData-0.0.4.dist-info/METADATA
PFAS_SAT_InputData-0.0.4.dist-info/WHEEL
PFAS_SAT_InputData-0.0.4.dist-info/top_level.txt
PFAS_SAT_InputData-0.0.4.dist-info/RECORD
